fudster/__init__.py
fudster/api/__init__.py
fudster/api/cors.py
fudster/api/routes.py
fudster/api/websockets.py
fudster/apps/__init__.py
fudster/apps/runelite.py
fudster/models/__init__.py
fudster/models/broadcast_models.py
fudster-1.0.3.dist-info/METADATA
fudster-1.0.3.dist-info/WHEEL
fudster-1.0.3.dist-info/RECORD
